ai_shell/__init__.py
ai_shell/__main__.py
ai_shell/ai.py
ai_shell/aishell.py
ai_shell/describe.py
ai_shell/logger.py
ai_shell/models.py
ai_shell/shell.py
ai_shell/util.py
ai_shell_loop-0.1.4.dist-info/licenses/LICENSE
ai_shell_loop-0.1.4.dist-info/METADATA
ai_shell_loop-0.1.4.dist-info/WHEEL
ai_shell_loop-0.1.4.dist-info/entry_points.txt
ai_shell_loop-0.1.4.dist-info/top_level.txt
ai_shell_loop-0.1.4.dist-info/RECORD
