Metadata-Version: 2.4
Name: ai-shell-loop
Version: 0.1.4
Summary: A command line tool that lets an AI do work for you.
Home-page: https://github.com/happyherp/ai-shell-loop
Author: Carlos Freund
Author-email: carlosfreund@gmail.com
License: Apache License 2.0
Classifier: Programming Language :: Python :: 3
Classifier: License :: OSI Approved :: Apache Software License
Classifier: Operating System :: POSIX :: Linux
Classifier: Operating System :: MacOS :: MacOS X
Requires-Python: >=3.6
License-File: LICENSE
Requires-Dist: openai==1.70.0
Requires-Dist: pydantic==2.9.1
Requires-Dist: PyYAML==6.0.2
Requires-Dist: appdirs==1.4.4
Dynamic: author
Dynamic: author-email
Dynamic: classifier
Dynamic: description
Dynamic: description-content-type
Dynamic: home-page
Dynamic: license
Dynamic: license-file
Dynamic: requires-dist
Dynamic: requires-python
Dynamic: summary
